fabric_text_processor/base_processor.py
fabric_text_processor/utils.py
fabric_text_processor-0.1.6.dist-info/METADATA
fabric_text_processor-0.1.6.dist-info/WHEEL
fabric_text_processor-0.1.6.dist-info/RECORD
