Metadata-Version: 2.1
Name: fabric-text-processor
Version: 0.1.6
Summary: 
Author: Shuyi Wang
Author-email: nkwshuyi@gmail.com
Requires-Python: >=3.12,<4.0
Classifier: Programming Language :: Python :: 3
Classifier: Programming Language :: Python :: 3.12
Requires-Dist: langchain-text-splitters (>=0.2.2,<0.3.0)
Requires-Dist: tiktoken (>=0.7.0,<0.8.0)
